jerryrigserialgen/README.MD
jerryrigserialgen/__init__.py
jerryrigserialgen/requirements.txt
jerryrigserialgen/thirdparty.json
jerryrigserialgen-0.12.dist-info/LICENSE.rst
jerryrigserialgen-0.12.dist-info/METADATA
jerryrigserialgen-0.12.dist-info/WHEEL
jerryrigserialgen-0.12.dist-info/top_level.txt
jerryrigserialgen-0.12.dist-info/RECORD
