Metadata-Version: 2.1
Name: jerryrigserialgen
Version: 0.12
Summary: jerry-rigged license system with UUID check (preventing more than one installation) and expiration date
Home-page: https://github.com/hansalemaos/jerryrigserialgen
Author: Johannes Fischer
Author-email: aulasparticularesdealemaosp@gmail.com
License: MIT
Keywords: UUID,license system,expiration date,serial number
Classifier: Development Status :: 4 - Beta
Classifier: Programming Language :: Python :: 3 :: Only
Classifier: Programming Language :: Python :: 3.10
Classifier: Topic :: Software Development :: Libraries :: Python Modules
Classifier: Topic :: Utilities
License-File: LICENSE.rst
Requires-Dist: cryptography
Requires-Dist: dill
Requires-Dist: isiter
Requires-Dist: pycryptodomex
Requires-Dist: requests
Requires-Dist: touchtouch
Requires-Dist: xxhash
